mlitlab/__init__.py
mlitlab/main.py
mlitlab/codes/1.txt
mlitlab/codes/10.txt
mlitlab/codes/11.txt
mlitlab/codes/12.txt
mlitlab/codes/13.txt
mlitlab/codes/14.txt
mlitlab/codes/2.txt
mlitlab/codes/3.txt
mlitlab/codes/4.txt
mlitlab/codes/5.txt
mlitlab/codes/6.txt
mlitlab/codes/7.txt
mlitlab/codes/8.txt
mlitlab/codes/9.txt
mlitlab-0.0.1.dist-info/METADATA
mlitlab-0.0.1.dist-info/WHEEL
mlitlab-0.0.1.dist-info/top_level.txt
mlitlab-0.0.1.dist-info/RECORD
